spiderchef/__init__.py
spiderchef/cli.py
spiderchef/exceptions.py
spiderchef/recipe.py
spiderchef/settings.py
spiderchef/utils.py
spiderchef/steps/__init__.py
spiderchef/steps/asynchronous.py
spiderchef/steps/base.py
spiderchef/steps/conditional.py
spiderchef/steps/error.py
spiderchef/steps/extract.py
spiderchef/steps/format.py
spiderchef-0.1.1.dist-info/METADATA
spiderchef-0.1.1.dist-info/WHEEL
spiderchef-0.1.1.dist-info/entry_points.txt
spiderchef-0.1.1.dist-info/licenses/LICENSE
spiderchef-0.1.1.dist-info/RECORD
