Metadata-Version: 2.4
Name: spiderchef
Version: 0.1.1
Summary: A recipe based web scraping tool.
Project-URL: source, https://github.com/vonsteer/spiderchef
Author-email: Jesse Constante <jglconstante@gmail.com>
License: MIT License
License-File: LICENSE
Keywords: cli,crawler,crawling,framework,python,recipe,scraping,web-scraping,web-scraping-python,yaml
Classifier: Development Status :: 3 - Alpha
Classifier: Framework :: AsyncIO
Classifier: Intended Audience :: Developers
Classifier: Intended Audience :: Information Technology
Classifier: License :: OSI Approved :: MIT License
Classifier: Natural Language :: English
Classifier: Operating System :: OS Independent
Classifier: Programming Language :: Python
Classifier: Programming Language :: Python :: 3
Classifier: Programming Language :: Python :: 3 :: Only
Classifier: Programming Language :: Python :: 3.10
Classifier: Programming Language :: Python :: 3.11
Classifier: Programming Language :: Python :: 3.12
Classifier: Programming Language :: Python :: 3.13
Classifier: Topic :: Software Development
Classifier: Topic :: Software Development :: Libraries
Classifier: Topic :: Software Development :: Libraries :: Python Modules
Classifier: Topic :: System :: Networking
Classifier: Typing :: Typed
Requires-Python: >=3.10
Requires-Dist: curl-cffi>=0.10.0
Requires-Dist: environs>=14.1.1
Requires-Dist: lxml>=5.4.0
Requires-Dist: orjson>=3.10.18
Requires-Dist: pydantic-extra-types>=2.10.4
Requires-Dist: pydantic>=2.11.4
Requires-Dist: pydash>=8.0.5
Requires-Dist: pyyaml>=6.0.2
Requires-Dist: semver>=3.0.4
Requires-Dist: structlog>=25.3.0
